README.md
setup.py
FantasyNameGenerator/Base.py
FantasyNameGenerator/DnD.py
FantasyNameGenerator/Items.py
FantasyNameGenerator/Pathfinder.py
FantasyNameGenerator/Stores.py
FantasyNameGenerator/__init__.py
FantasyNameGenerator/dnd.py
FantasyNameGenerator.egg-info/PKG-INFO
FantasyNameGenerator.egg-info/SOURCES.txt
FantasyNameGenerator.egg-info/dependency_links.txt
FantasyNameGenerator.egg-info/top_level.txt
tests/test_DnD.py
tests/test_Items.py
tests/test_Pathfinder.py
tests/test_Stores.py