Metadata-Version: 2.1
Name: FantasyNameGenerator
Version: 0.0.5
Summary: A name generator from various worlds of fantasy
Project-URL: Source, https://github.com/Dude036/FantasyNameGenerator
Classifier: Programming Language :: Python :: 3 :: Only
Classifier: Development Status :: 2 - Pre-Alpha
